flask_bulbs.py
setup.py
Flask_Bulbs.egg-info/PKG-INFO
Flask_Bulbs.egg-info/SOURCES.txt
Flask_Bulbs.egg-info/dependency_links.txt
Flask_Bulbs.egg-info/not-zip-safe
Flask_Bulbs.egg-info/requires.txt
Flask_Bulbs.egg-info/top_level.txt