Metadata-Version: 1.1
Name: Flask-Bulbs
Version: 0.1
Summary: Flask extension for [Bulbs](http://bulbflow.com/) supporting the factory pattern with the init_app method.
Home-page: http://github.com/peterhil/flask-bulbs/
Author: Peter Hillerström
Author-email: peter.hillerstrom@gmail.com
License: MIT
Platform: any
Classifier: Environment :: Web Environment
Classifier: Intended Audience :: Developers
Classifier: License :: OSI Approved :: MIT License
Classifier: Operating System :: OS Independent
Classifier: Programming Language :: Python
Classifier: Topic :: Internet :: WWW/HTTP :: Dynamic Content
Classifier: Topic :: Software Development :: Libraries :: Python Modules
